{
  "type": "object",
  "properties": {
    "countryCode": {
      "type": "string"
    },
    "companyId": {
      "type": "string"
    },
    "pagination": {
      "type": "object",
      "properties": {
        "offset": {
          "type": "number"
        },
        "limit": {
          "type": "number"
        },
        "total": {
          "type": "number"
        }
      }
    },
    "descriptions": {
      "type": "array",
      "items": {
        "type": "object",
        "properties": {
          "text": {
            "type": "string"
          },
          "url": {
            "type": "string"
          },
          "source": {
            "type": "string"
          }
        }
      }
    }
  },
  "additionalProperties": false
}
